instabot/__init__.py
instabot/__main__.py
instabot/bot.py
instabot/default_config.py
instabot/persistence/__init__.py
instabot/persistence/manager.py
instabot/persistence/sql.py
instabot_py/__init__.py
instabot_py/__main__.py
instabot_py/check_status.py
instabot_py/config.py
instabot_py/default_config.py
instabot_py/feed_scanner.py
instabot_py/follow_protocol.py
instabot_py/instabot.py
instabot_py/interactive.py
instabot_py/likers_graber_protocol.py
instabot_py/likers_protocol.py
instabot_py/new_auto_mod_like2.py
instabot_py/new_auto_mod_likeall.py
instabot_py/new_auto_mod_unfollow2.py
instabot_py/new_unfollow.py
instabot_py/post_page.py
instabot_py/recent_feed.py
instabot_py/sql_updates.py
instabot_py/unfollow_protocol.py
instabot_py/unfollowpub.py
instabot_py/user_feed.py
instabot_py/user_feed_protocol.py
instabot_py/user_info.py
instabot_py/userinfo.py
instabot_py/username_checker.py
instabot_py/persistence/__init__.py
instabot_py/persistence/manager.py
instabot_py/persistence/sql.py
neo_instabot-0.6.0.dist-info/LICENSE
neo_instabot-0.6.0.dist-info/METADATA
neo_instabot-0.6.0.dist-info/WHEEL
neo_instabot-0.6.0.dist-info/entry_points.txt
neo_instabot-0.6.0.dist-info/top_level.txt
neo_instabot-0.6.0.dist-info/RECORD
