Metadata-Version: 2.1
Name: neo-instabot
Version: 0.6.0
Summary: Instagram Python Bot
Home-page: https://github.com/yurilaaziz/bot.py
Author: Amine Ben Asker
Author-email: ben.asker.amine@gmail.com
License: MIT
Download-URL: https://github.com/yurilaaziz/bot.py/tarball/master
Keywords: instagram bot,Instagram web API hack,automation tool.
Platform: UNKNOWN
Classifier: Development Status :: 5 - Production/Stable
Classifier: Intended Audience :: Developers
Classifier: Topic :: Software Development :: Build Tools
Classifier: License :: OSI Approved :: MIT License
Classifier: Programming Language :: Python :: 3
Classifier: Programming Language :: Python :: 3.6
Classifier: Programming Language :: Python :: 3.7
Classifier: Programming Language :: Python :: 3.8
Requires-Python: >3.6.1
Requires-Dist: fake-useragent (==0.1.11)
Requires-Dist: instaloader (==4.2.8)
Requires-Dist: requests (==2.22.0)
Requires-Dist: blessings (==1.7.0)
Requires-Dist: config42 (==0.4.2)
Requires-Dist: sqlalchemy (==1.3.4)
Requires-Dist: PyYAML (==5.1.0)
